README.md
pyproject.toml
src/tsdbpy/__init__.py
src/tsdbpy/conn.py
src/tsdbpy/db_utils.py
src/tsdbpy/enums.py
src/tsdbpy/metrics.py
src/tsdbpy/source.py
src/tsdbpy/tag.py
src/tsdbpy/tsdata.py
src/tsdbpy/units.py
src/tsdbpy.egg-info/PKG-INFO
src/tsdbpy.egg-info/SOURCES.txt
src/tsdbpy.egg-info/dependency_links.txt
src/tsdbpy.egg-info/requires.txt
src/tsdbpy.egg-info/top_level.txt
tests/test_conn.py
tests/test_metric.py
tests/test_source.py
tests/test_tag.py
tests/test_tsdata.py
tests/test_units.py