Metadata-Version: 2.4
Name: tsdbpy
Version: 0.3.3
Summary: tsdbpy - Python TimescaleDB SDK for Tai-Ji Control
Author-email: KangkangZhang <kkzhang3@hotmail.com>
License: MIT
Keywords: database,tsdb,python package
Requires-Python: >=3.8
Requires-Dist: psycopg[binary]
Requires-Dist: loguru
